genrate/__init__.py
ai_content_generator-0.1.0.dist-info/METADATA
ai_content_generator-0.1.0.dist-info/WHEEL
ai_content_generator-0.1.0.dist-info/top_level.txt
ai_content_generator-0.1.0.dist-info/RECORD
